progeny/__init__.py
progeny-0.2.0.dist-info/LICENSE.txt
progeny-0.2.0.dist-info/METADATA
progeny-0.2.0.dist-info/WHEEL
progeny-0.2.0.dist-info/top_level.txt
progeny-0.2.0.dist-info/RECORD
