Metadata-Version: 2.1
Name: progeny
Version: 0.2.0
Summary: Simple but powerful management for complex class hierarchies
Home-page: https://github.com/GoodRx/progeny
Author: Andy Freeland
Author-email: andy@goodrx.com
License: MIT
Platform: UNKNOWN
Classifier: Development Status :: 4 - Beta
Classifier: Intended Audience :: Developers
Classifier: Natural Language :: English
Classifier: License :: OSI Approved :: MIT License
Classifier: Programming Language :: Python
Classifier: Programming Language :: Python :: 3
Classifier: Programming Language :: Python :: 3.7
Classifier: Programming Language :: Python :: 3.8
Classifier: Programming Language :: Python :: Implementation :: CPython
Classifier: Programming Language :: Python :: Implementation :: PyPy
